LICENSE
README.md
setup.py
evaics/__init__.py
evaics.ml.egg-info/PKG-INFO
evaics.ml.egg-info/SOURCES.txt
evaics.ml.egg-info/dependency_links.txt
evaics.ml.egg-info/requires.txt
evaics.ml.egg-info/top_level.txt
evaics/ml/__init__.py
evaics/ml/learning.py