Metadata-Version: 2.1
Name: evaics.ml
Version: 0.1.3
Summary: EVA ICS v4 Machine Learning Kit
Home-page: https://github.com/eva-ics/eva-mlkit-client-python
Author: Bohemia Automation / Altertech
Author-email: div@altertech.com
License: Apache License 2.0
Platform: UNKNOWN
Classifier: Programming Language :: Python :: 3
Classifier: License :: OSI Approved :: Apache Software License
Classifier: Topic :: Software Development :: Libraries
Classifier: Topic :: Scientific/Engineering :: Artificial Intelligence
License-File: LICENSE
